{
  "DhammaLink": [{
    "LinkID": 15,
    "LinkAddress": "http://www.oba.org.tw",
    "ClickCount": 0,
    "Description": "台湾原始佛教协会",
    "Remark": null,
    "IndexNo": 0,
    "Type": 3
  }, {
    "LinkID": 21,
    "LinkAddress": "http://blog.sina.com.cn/u/3973309727",
    "ClickCount": 0,
    "Description": "泰国禅修之窗",
    "Remark": null,
    "IndexNo": 0,
    "Type": 3
  }, {
    "LinkID": 24,
    "LinkAddress": "http://www.theravadins.org",
    "ClickCount": 0,
    "Description": "南传上座部佛教",
    "Remark": "",
    "IndexNo": 0,
    "Type": 3
  }, {
    "LinkID": 29,
    "LinkAddress": "http://dict.sutta.org",
    "ClickCount": 0,
    "Description": "巴利语辞典",
    "Remark": "",
    "IndexNo": 1,
    "Type": 3
  }, {
    "LinkID": 40,
    "LinkAddress": "http://yifertw.blogspot.com/",
    "ClickCount": 0,
    "Description": "台语与佛典(需翻*墙)",
    "Remark": "",
    "IndexNo": 3,
    "Type": 3
  }, {
    "LinkID": 50,
    "LinkAddress": "http://www.dhammarain.org.tw/canon/canon1.html",
    "ClickCount": 0,
    "Description": "法雨道场",
    "Remark": "",
    "IndexNo": 3,
    "Type": 3
  }, {
    "LinkID": 55,
    "LinkAddress": "http://wiki.sutta.org/wiki/%E9%A6%96%E9%A1%B5",
    "ClickCount": 0,
    "Description": "上座部佛教百科",
    "Remark": null,
    "IndexNo": 4,
    "Type": 3
  }, {
    "LinkID": 57,
    "LinkAddress": "http://kusala.online-dhamma.net/文字資料/南傳佛教圖書館%20Theravada%20Buddhism%20E-Library/",
    "ClickCount": 0,
    "Description": "南傳佛教圖書館",
    "Remark": null,
    "IndexNo": 0,
    "Type": 3
  }, {
    "LinkID": 68,
    "LinkAddress": "http://dharmaseed.org",
    "ClickCount": 0,
    "Description": "Dharma seed",
    "Remark": "",
    "IndexNo": 1,
    "Type": 3
  }, {
    "LinkID": 69,
    "LinkAddress": "https://www.dhamma.com/zh/",
    "ClickCount": 0,
    "Description": "Dhamma.com",
    "Remark": "",
    "IndexNo": 1,
    "Type": 3
  }, {
    "LinkID": 74,
    "LinkAddress": "http://forestdhamma.org",
    "ClickCount": 0,
    "Description": "Forest Dhamma",
    "Remark": "",
    "IndexNo": 1,
    "Type": 3
  }],
  "Result": true,
  "ErrorMsg": ""
}